DirectoryFormula/Directory.py
DirectoryFormula/__init__.py
DirectoryFormulas/Directories.py
DirectoryFormulas/Directory.py
DirectoryFormulas/FunctionsBacktesting.py
DirectoryFormulas/FunctionsOPT.py
DirectoryFormulas/__init__.py
DirectoryFormulas-1.3.2.dist-info/METADATA
DirectoryFormulas-1.3.2.dist-info/WHEEL
DirectoryFormulas-1.3.2.dist-info/top_level.txt
DirectoryFormulas-1.3.2.dist-info/RECORD
